namewiz/__init__.py
namewiz/__main__.py
namewiz/namewiz.py
namewiz-0.4.0.dist-info/WHEEL
namewiz-0.4.0.dist-info/METADATA
namewiz-0.4.0.dist-info/RECORD
