Metadata-Version: 2.1
Name: namewiz
Version: 0.4.0
Summary: a tool for generating the filename for a CSNTM CaptureOne session
License: MIT
Author: David Flood
Author-email: davidfloodii@gmail.com
Requires-Python: >=3.10,<4.0
Classifier: License :: OSI Approved :: MIT License
Classifier: Programming Language :: Python :: 3
Classifier: Programming Language :: Python :: 3.10
Requires-Dist: PySimpleGUI (>=4.57.0,<5.0.0)
